rosegeomap/__init__.py
rosegeomap/common.py
rosegeomap/rosegeomap.py
rosegeomap/toolbar.py
rosegeomap/utils.py
rosegeomap-0.0.4.dist-info/LICENSE
rosegeomap-0.0.4.dist-info/METADATA
rosegeomap-0.0.4.dist-info/WHEEL
rosegeomap-0.0.4.dist-info/dependency_links.txt
rosegeomap-0.0.4.dist-info/top_level.txt
rosegeomap-0.0.4.dist-info/RECORD
