Metadata-Version: 2.1
Name: rosegeomap
Version: 0.0.4
Summary: An Interactive Mapping Package
Home-page: https://github.com/crose26/rosegeomap
Author: Caleb Rose
Author-email: crose26@vols.utk.edu
License: MIT license
Keywords: rosegeomap
Platform: UNKNOWN
Classifier: Development Status :: 2 - Pre-Alpha
Classifier: Intended Audience :: Developers
Classifier: License :: OSI Approved :: MIT License
Classifier: Natural Language :: English
Classifier: Programming Language :: Python :: 3
Classifier: Programming Language :: Python :: 3.5
Classifier: Programming Language :: Python :: 3.6
Classifier: Programming Language :: Python :: 3.7
Classifier: Programming Language :: Python :: 3.8
Requires-Python: >=3.5
Requires-Dist: earthengine-api
Requires-Dist: folium
Requires-Dist: geopandas
Requires-Dist: ipyfilechooser
Requires-Dist: ipyleaflet
Requires-Dist: matplotlib
Requires-Dist: pyshp
Requires-Dist: whitebox (>=1.4.1)
Requires-Dist: whiteboxgui
